django_sync_github_teams/__init__.py
django_sync_github_teams/apps.py
django_sync_github_teams/sync.py
django_sync_github_teams/management/commands/sync-github-teams.py
django_sync_github_teams-0.2.0.dist-info/LICENSE
django_sync_github_teams-0.2.0.dist-info/WHEEL
django_sync_github_teams-0.2.0.dist-info/METADATA
django_sync_github_teams-0.2.0.dist-info/RECORD
