Metadata-Version: 2.1
Name: django-sync-github-teams
Version: 0.2.0
Summary: django-sync-github-teams is ...
Author-email: Antonio Terceiro <antonio.terceiro@linaro.org>
Classifier: License :: OSI Approved :: MIT License
Requires-Dist: django-allauth>=0.44
Requires-Dist: Django>=3.2
Project-URL: Home, https://gitlab.com/Linaro/django-sync-github-teams
